MANIFEST.in
README.md
setup.py
jupyter_share_session/__init__.py
jupyter_share_session/decorator.py
jupyter_share_session/magic.py
jupyter_share_session/sharesession.html
jupyter_share_session.egg-info/PKG-INFO
jupyter_share_session.egg-info/SOURCES.txt
jupyter_share_session.egg-info/dependency_links.txt
jupyter_share_session.egg-info/not-zip-safe
jupyter_share_session.egg-info/top_level.txt