Metadata-Version: 1.0
Name: jupyter-share-session
Version: 0.2.4
Summary: Split a notebook into multiple files.
Home-page: http://github.com/waynebliu/jupyter_share_session/
Author: Wayne Liu
Author-email: waynebliu@yahoo.com
License: MIT
Platform: UNKNOWN
